pgjobq/__init__.py
pgjobq/_crud.py
pgjobq/_exceptions.py
pgjobq/_filters.py
pgjobq/_migrations/1.up.sql
pgjobq/_migrations/__init__.py
pgjobq/_queries.py
pgjobq/_queue.py
pgjobq/_sql/ack.sql
pgjobq/_sql/cancel.sql
pgjobq/_sql/cleanup.sql
pgjobq/_sql/gather_completed.sql
pgjobq/_sql/heartbeat.sql
pgjobq/_sql/nack.sql
pgjobq/_sql/poll.sql
pgjobq/_sql/publish.sql
pgjobq/_sql/statistics.sql
pgjobq/_telemetry.py
pgjobq/api.py
pgjobq/py.typed
pgjobq/types.py
pgjobq-0.10.0.dist-info/LICENSE.txt
pgjobq-0.10.0.dist-info/WHEEL
pgjobq-0.10.0.dist-info/METADATA
pgjobq-0.10.0.dist-info/RECORD
