Metadata-Version: 2.1
Name: pgjobq
Version: 0.10.0
Summary: PostgreSQL backed job queues
Home-page: https://github.com/adriangb/pgjobq
License: MIT
Author: Adrian Garcia Badaracco
Author-email: dev@adriangb.com
Requires-Python: >=3.7,<4
Classifier: License :: OSI Approved :: MIT License
Classifier: Programming Language :: Python :: 3
Classifier: Programming Language :: Python :: 3.7
Classifier: Programming Language :: Python :: 3.8
Classifier: Programming Language :: Python :: 3.9
Classifier: Programming Language :: Python :: 3.10
Classifier: Programming Language :: Python :: 3.11
Requires-Dist: anyio (>=3.6.1,<3.7.0)
Requires-Dist: asyncpg (>=0.26.0,<0.27.0)
Requires-Dist: typing-extensions (>=4.3.0,<5.0.0); python_version < "3.8"
